{
    "id": "cre/fa/aws/data_analytics",
    "name": "AWS Data Analytics",
    "practice_area": "AWS Data",
    "primary_skills": [
        "aws/category/analytics",
        "aws/service/amazon-athena",
        "aws/service/amazon-cloudsearch",
        "aws/service/amazon-healthlake",
        "aws/service/amazon-opensearch-service",
        "aws/service/amazon-quicksight",
        "aws/service/amazon-redshift",
        "aws/service/aws-lake-formation"
    ],
    "secondary_skills": [
        "aws/category/databases"
    ],
    "exceptions": [
        "Amazon DataZone (Preview)"
    ]
}