{
    "id": "cre/fa/aws/databases",
    "name": "AWS Databases",
    "practice_area": "AWS Data",
    "primary_skills": [
        "aws/category/databases",
        "aws/service/amazon-aurora",
        "aws/service/amazon-documentdb-with-mongodb-compatibility",
        "aws/service/amazon-dynamodb",
        "aws/service/amazon-elasticache",
        "aws/service/amazon-keyspaces-for-apache-cassandra",
        "aws/service/amazon-memorydb-for-redis",
        "aws/service/amazon-neptune",
        "aws/service/amazon-rds",
        "aws/service/amazon-timestream",
        "aws/service/aws-database-migration-service"
    ],
    "secondary_skills": []
}